{"id":"ec","termCount":9,"terms":[{"id":"eca-net-efficient-channel-attention","slug":"eca-net-efficient-channel-attention","title":"ECA-Net (Efficient Channel Attention)","aliases":["ECA-Net","Efficient Channel Attention"],"summary":"ECA-Net (Efficient Channel Attention) belongs to the Neural Networks area of AI/ML, within Attention Mechanism. It sits inside Neural Networks / Attention Mechanism. Start after Attention U-Net and Channel Attention.","taxonomy":{"topic":"ECA-Net (Efficient Channel Attention)","category":"Neural Networks","subCategory":"Attention Mechanism","tags":["neural-networks","attention-mechanism"]},"autoClassified":true,"links":{"prerequisites":["Attention U-Net","Channel Attention","U-Net"],"related":["ECANet (Efficient Channel Attention)","Channel Attention","Attention U-Net","Channel-Wise Attention Techniques"],"alternatives":[],"next":[]},"blocks":[{"id":"overview","type":"markdown","title":"Overview","body":"ECA-Net (Efficient Channel Attention) belongs to the Neural Networks area of AI/ML, within Attention Mechanism. It sits inside Neural Networks / Attention Mechanism. Start after Attention U-Net and Channel Attention."},{"id":"taxonomy","type":"bullets","title":"Field Position","items":["Category: Neural Networks","Sub-category: Attention Mechanism"]},{"id":"connections","type":"bullets","title":"Connection Map","items":["Prerequisites: Attention U-Net, Channel Attention, U-Net","Related: ECANet (Efficient Channel Attention), Channel Attention, Attention U-Net, Channel-Wise Attention Techniques"]},{"id":"study-prompts","type":"steps","title":"Study Prompts","steps":[{"label":"Situate it","body":"Place this term inside Neural Networks / Attention Mechanism before you memorize the wording."},{"label":"Define it","body":"Write the term in your own words before memorizing a textbook phrasing."},{"label":"Trace the graph","body":"Follow one prerequisite and one downstream concept from the learning graph."},{"label":"Record an example","body":"Capture an example, use case, or implementation note in your personal notebook."}]},{"id":"why-it-matters","type":"markdown","title":"Why It Matters","body":"Watch how the concept affects layers, activations, gradients, optimization, or training dynamics."},{"id":"comparison-notes","type":"bullets","title":"Comparison Notes","items":["Before this term, get comfortable with Attention U-Net and Channel Attention.","Compare it with ECANet (Efficient Channel Attention) and Channel Attention to separate overlap from difference."]},{"id":"recall-drill","type":"steps","title":"Recall Drill","steps":[{"label":"Say it simply","body":"Rewrite ECA-Net (Efficient Channel Attention) in one sentence before trying to preserve the source wording."},{"label":"Place it","body":"Watch how the concept affects layers, activations, gradients, optimization, or training dynamics."},{"label":"Link it","body":"Connect it to ECANet (Efficient Channel Attention) and Channel Attention and one downstream idea from the graph."},{"label":"Review first","body":"Check Attention U-Net and Channel Attention so you can see what this term assumes."}]},{"id":"at-a-glance","type":"table","title":"At a Glance","rows":[{"label":"Family","value":"Neural Networks / Attention Mechanism"},{"label":"Best first read","value":"Attention U-Net and Channel Attention"},{"label":"Best comparison","value":"ECANet (Efficient Channel Attention) and Channel Attention"},{"label":"Next step","value":"Use the recall drill"},{"label":"Remember","value":"Watch how the concept affects layers, activations, gradients, optimization, or training dynamics."}]},{"id":"visual-summary","type":"callout","title":"Visual Summary","tone":"info","body":"Watch how the concept affects layers, activations, gradients, optimization, or training dynamics."},{"id":"curriculum-map","type":"curriculum-map","title":"Curriculum Map","sections":[{"section":"Introduction","status":"direct","runtimeBlocks":["overview","taxonomy"],"note":"The opening definition, context, and classification are always visible."},{"section":"Prerequisites","status":"direct","runtimeBlocks":["study-prompts","connections"],"note":"Prerequisite framing is handled by the study sequence and concept graph."},{"section":"Theoretical Concepts","status":"partial","runtimeBlocks":["overview","why-it-matters","recall-drill"],"note":"Core intuition is present, while deeper math-heavy expansion remains editorial backlog."},{"section":"How It Works","status":"direct","runtimeBlocks":["study-prompts","connections"],"note":"The step sequence and relation map carry the process explanation."},{"section":"Variants or Extensions","status":"direct","runtimeBlocks":["connections","comparison-notes"],"note":"Alternatives and neighboring labels are surfaced through graph and comparison blocks."},{"section":"Applications","status":"direct","runtimeBlocks":["overview","why-it-matters"],"note":"The summary and editorial note show relevance before deeper examples are added."},{"section":"Implementation","status":"direct","runtimeBlocks":["study-prompts","recall-drill"],"note":"Implementation thinking is supported by the guided sequence and recall practice."},{"section":"Evaluation and Metrics","status":"direct","runtimeBlocks":["comparison-notes","recall-drill"],"note":"Tradeoffs, comparison, and recall drills anchor evaluation thinking."},{"section":"Advantages and Disadvantages","status":"direct","runtimeBlocks":["comparison-notes","why-it-matters"],"note":"The current blocks already surface tradeoffs and framing."},{"section":"Ethics and Responsible AI","status":"direct","runtimeBlocks":["why-it-matters","comparison-notes"],"note":"Responsible-AI framing is visible in the editorial layer and comparison notes."},{"section":"Related Concepts","status":"direct","runtimeBlocks":["connections"],"note":"The concept graph is already a first-class runtime block."}]},{"id":"comparison","type":"comparison","title":"Compare and Contrast","panels":[{"label":"What it is","tone":"accent","body":"ECA-Net (Efficient Channel Attention) belongs to the Neural Networks area of AI/ML, within Attention Mechanism."},{"label":"What it is not","tone":"secondary","body":"It is not just ECANet (Efficient Channel Attention) and Channel Attention; the graph shows how it sits inside Neural Networks."},{"label":"Common confusion","tone":"gold","body":"Ask whether the term changes layers, activations, gradients, optimization, or training dynamics. Compare it against ECANet (Efficient Channel Attention) and Channel Attention so the boundary stays visible instead of collapsing into a synonym pile."},{"label":"Best next step","tone":"accent","body":"Review Attention U-Net and Channel Attention first, then move toward the next connected concept."}],"takeaway":"The comparison view keeps ECA-Net (Efficient Channel Attention) honest by showing the nearest neighbors, the real boundary, and the next study move."},{"id":"concept-map","type":"diagram","title":"Concept Map","center":{"label":"ECA-Net (Efficient Channel Attention)","caption":"Neural Networks / Attention Mechanism"},"lanes":[{"label":"Before","tone":"accent","items":["Attention U-Net","Channel Attention","U-Net"]},{"label":"Compare","tone":"secondary","items":["ECANet (Efficient Channel Attention)","Channel Attention","Attention U-Net"]},{"label":"After","tone":"gold","items":[]}],"takeaway":"Read ECA-Net (Efficient Channel Attention) as a node inside its learning graph: predecessor concepts give context, neighbors sharpen comparison, and next concepts show where the topic expands."},{"id":"quick-faq","type":"faq","title":"Quick FAQ","items":[{"question":"What is ECA-Net (Efficient Channel Attention) in one sentence?","answer":"ECA-Net (Efficient Channel Attention) belongs to the Neural Networks area of AI/ML, within Attention Mechanism. It sits inside Neural Networks / Attention Mechanism. Start after Attention U-Net and Channel Attention."},{"question":"What should I know before studying ECA-Net (Efficient Channel Attention)?","answer":"Start with Attention U-Net and Channel Attention."},{"question":"What should I compare ECA-Net (Efficient Channel Attention) with?","answer":"Compare it with ECANet (Efficient Channel Attention) and Channel Attention before moving on to ."}]},{"id":"quick-quiz","type":"quiz","title":"Quick Check","question":"What should you review first before studying ECA-Net (Efficient Channel Attention)?","options":["Review Attention U-Net","Jump to ECANet (Efficient Channel Attention)","Memorize the title only","Skip straight to the next topic"],"answerIndex":0,"explanation":"ECA-Net (Efficient Channel Attention) sits after Attention U-Net, so that prerequisite gives you the assumptions and vocabulary you need before the deeper block stack makes sense."}],"metadata":{"difficulty":"","maturity":"source-imported","studyFamily":"Neural Networks","editorialTier":"standard"},"artifact":{"shardId":"ec"},"source":{"glossaryWorkbook":{"file":"data_glossary.xlsx","sheetName":"main","inventoryRows":[5415,9197],"inventoryCells":["A5415","D9197","E9197"],"inventoryColumns":["A","D","E"],"sourceCells":[{"rowNumber":5415,"columnIndex":1,"columnLetter":"A"},{"rowNumber":9197,"columnIndex":4,"columnLetter":"D"},{"rowNumber":9197,"columnIndex":5,"columnLetter":"E"}],"taxonomyRow":0,"definitionRow":null,"definitionBody":null}}},{"id":"ecanet-efficient-channel-attention","slug":"ecanet-efficient-channel-attention","title":"ECANet (Efficient Channel Attention)","aliases":["ECANet","Efficient Channel Attention"],"summary":"ECANet (Efficient Channel Attention) belongs to the Neural Networks area of AI/ML, within Attention Mechanism. It sits inside Neural Networks / Attention Mechanism. Start after Channel Attention.","taxonomy":{"topic":"ECANet (Efficient Channel Attention)","category":"Neural Networks","subCategory":"Attention Mechanism","tags":["neural-networks","attention-mechanism"]},"autoClassified":true,"links":{"prerequisites":["Channel Attention"],"related":["ECA-Net (Efficient Channel Attention)","Channel Attention","Channel-Wise Attention Techniques","Channel-Wise Attention Enhancements"],"alternatives":[],"next":[]},"blocks":[{"id":"overview","type":"markdown","title":"Overview","body":"ECANet (Efficient Channel Attention) belongs to the Neural Networks area of AI/ML, within Attention Mechanism. It sits inside Neural Networks / Attention Mechanism. Start after Channel Attention."},{"id":"taxonomy","type":"bullets","title":"Field Position","items":["Category: Neural Networks","Sub-category: Attention Mechanism"]},{"id":"connections","type":"bullets","title":"Connection Map","items":["Prerequisites: Channel Attention","Related: ECA-Net (Efficient Channel Attention), Channel Attention, Channel-Wise Attention Techniques, Channel-Wise Attention Enhancements"]},{"id":"study-prompts","type":"steps","title":"Study Prompts","steps":[{"label":"Situate it","body":"Place this term inside Neural Networks / Attention Mechanism before you memorize the wording."},{"label":"Define it","body":"Write the term in your own words before memorizing a textbook phrasing."},{"label":"Trace the graph","body":"Follow one prerequisite and one downstream concept from the learning graph."},{"label":"Record an example","body":"Capture an example, use case, or implementation note in your personal notebook."}]},{"id":"why-it-matters","type":"markdown","title":"Why It Matters","body":"Watch how the concept affects layers, activations, gradients, optimization, or training dynamics."},{"id":"comparison-notes","type":"bullets","title":"Comparison Notes","items":["Before this term, get comfortable with Channel Attention.","Compare it with ECA-Net (Efficient Channel Attention) and Channel Attention to separate overlap from difference."]},{"id":"recall-drill","type":"steps","title":"Recall Drill","steps":[{"label":"Say it simply","body":"Rewrite ECANet (Efficient Channel Attention) in one sentence before trying to preserve the source wording."},{"label":"Place it","body":"Watch how the concept affects layers, activations, gradients, optimization, or training dynamics."},{"label":"Link it","body":"Connect it to ECA-Net (Efficient Channel Attention) and Channel Attention and one downstream idea from the graph."},{"label":"Review first","body":"Check Channel Attention so you can see what this term assumes."}]},{"id":"at-a-glance","type":"table","title":"At a Glance","rows":[{"label":"Family","value":"Neural Networks / Attention Mechanism"},{"label":"Best first read","value":"Channel Attention"},{"label":"Best comparison","value":"ECA-Net (Efficient Channel Attention) and Channel Attention"},{"label":"Next step","value":"Use the recall drill"},{"label":"Remember","value":"Watch how the concept affects layers, activations, gradients, optimization, or training dynamics."}]},{"id":"visual-summary","type":"callout","title":"Visual Summary","tone":"info","body":"Watch how the concept affects layers, activations, gradients, optimization, or training dynamics."},{"id":"curriculum-map","type":"curriculum-map","title":"Curriculum Map","sections":[{"section":"Introduction","status":"direct","runtimeBlocks":["overview","taxonomy"],"note":"The opening definition, context, and classification are always visible."},{"section":"Prerequisites","status":"direct","runtimeBlocks":["study-prompts","connections"],"note":"Prerequisite framing is handled by the study sequence and concept graph."},{"section":"Theoretical Concepts","status":"partial","runtimeBlocks":["overview","why-it-matters","recall-drill"],"note":"Core intuition is present, while deeper math-heavy expansion remains editorial backlog."},{"section":"How It Works","status":"direct","runtimeBlocks":["study-prompts","connections"],"note":"The step sequence and relation map carry the process explanation."},{"section":"Variants or Extensions","status":"direct","runtimeBlocks":["connections","comparison-notes"],"note":"Alternatives and neighboring labels are surfaced through graph and comparison blocks."},{"section":"Applications","status":"direct","runtimeBlocks":["overview","why-it-matters"],"note":"The summary and editorial note show relevance before deeper examples are added."},{"section":"Implementation","status":"direct","runtimeBlocks":["study-prompts","recall-drill"],"note":"Implementation thinking is supported by the guided sequence and recall practice."},{"section":"Evaluation and Metrics","status":"direct","runtimeBlocks":["comparison-notes","recall-drill"],"note":"Tradeoffs, comparison, and recall drills anchor evaluation thinking."},{"section":"Advantages and Disadvantages","status":"direct","runtimeBlocks":["comparison-notes","why-it-matters"],"note":"The current blocks already surface tradeoffs and framing."},{"section":"Ethics and Responsible AI","status":"direct","runtimeBlocks":["why-it-matters","comparison-notes"],"note":"Responsible-AI framing is visible in the editorial layer and comparison notes."},{"section":"Related Concepts","status":"direct","runtimeBlocks":["connections"],"note":"The concept graph is already a first-class runtime block."}]},{"id":"comparison","type":"comparison","title":"Compare and Contrast","panels":[{"label":"What it is","tone":"accent","body":"ECANet (Efficient Channel Attention) belongs to the Neural Networks area of AI/ML, within Attention Mechanism."},{"label":"What it is not","tone":"secondary","body":"It is not just ECA-Net (Efficient Channel Attention) and Channel Attention; the graph shows how it sits inside Neural Networks."},{"label":"Common confusion","tone":"gold","body":"Ask whether the term changes layers, activations, gradients, optimization, or training dynamics. Compare it against ECA-Net (Efficient Channel Attention) and Channel Attention so the boundary stays visible instead of collapsing into a synonym pile."},{"label":"Best next step","tone":"accent","body":"Review Channel Attention first, then move toward the next connected concept."}],"takeaway":"The comparison view keeps ECANet (Efficient Channel Attention) honest by showing the nearest neighbors, the real boundary, and the next study move."},{"id":"concept-map","type":"diagram","title":"Concept Map","center":{"label":"ECANet (Efficient Channel Attention)","caption":"Neural Networks / Attention Mechanism"},"lanes":[{"label":"Before","tone":"accent","items":["Channel Attention"]},{"label":"Compare","tone":"secondary","items":["ECA-Net (Efficient Channel Attention)","Channel Attention","Channel-Wise Attention Techniques"]},{"label":"After","tone":"gold","items":[]}],"takeaway":"Read ECANet (Efficient Channel Attention) as a node inside its learning graph: predecessor concepts give context, neighbors sharpen comparison, and next concepts show where the topic expands."},{"id":"quick-faq","type":"faq","title":"Quick FAQ","items":[{"question":"What is ECANet (Efficient Channel Attention) in one sentence?","answer":"ECANet (Efficient Channel Attention) belongs to the Neural Networks area of AI/ML, within Attention Mechanism. It sits inside Neural Networks / Attention Mechanism. Start after Channel Attention."},{"question":"What should I know before studying ECANet (Efficient Channel Attention)?","answer":"Start with Channel Attention."},{"question":"What should I compare ECANet (Efficient Channel Attention) with?","answer":"Compare it with ECA-Net (Efficient Channel Attention) and Channel Attention before moving on to ."}]},{"id":"quick-quiz","type":"quiz","title":"Quick Check","question":"What should you review first before studying ECANet (Efficient Channel Attention)?","options":["Review Channel Attention","Jump to ECA-Net (Efficient Channel Attention)","Memorize the title only","Skip straight to the next topic"],"answerIndex":0,"explanation":"ECANet (Efficient Channel Attention) sits after Channel Attention, so that prerequisite gives you the assumptions and vocabulary you need before the deeper block stack makes sense."}],"metadata":{"difficulty":"","maturity":"source-imported","studyFamily":"Neural Networks","editorialTier":"standard"},"artifact":{"shardId":"ec"},"source":{"glossaryWorkbook":{"file":"data_glossary.xlsx","sheetName":"main","inventoryRows":[5416,9462],"inventoryCells":["A5416","D9462","E9462"],"inventoryColumns":["A","D","E"],"sourceCells":[{"rowNumber":5416,"columnIndex":1,"columnLetter":"A"},{"rowNumber":9462,"columnIndex":4,"columnLetter":"D"},{"rowNumber":9462,"columnIndex":5,"columnLetter":"E"}],"taxonomyRow":0,"definitionRow":null,"definitionBody":null}}},{"id":"echo-state-networks","slug":"echo-state-networks","title":"Echo State Networks","aliases":[],"summary":"Echo State Networks is a glossary node in the AI/ML learning graph. Compare it with Continuous-Time Echo State Network (CT-ESN) and Echo State Networks (ESN). It opens into Echo State Networks (ESN) and Continuous-Time Echo State Network (CT-ESN).","taxonomy":{"topic":"Echo State Networks","category":"","subCategory":"","tags":[]},"autoClassified":false,"links":{"prerequisites":[],"related":["Continuous-Time Echo State Network (CT-ESN)","Echo State Networks (ESN)","State Space","State of the Art"],"alternatives":[],"next":["Echo State Networks (ESN)","Continuous-Time Echo State Network (CT-ESN)"]},"blocks":[{"id":"overview","type":"markdown","title":"Overview","body":"Echo State Networks is a glossary node in the AI/ML learning graph. Compare it with Continuous-Time Echo State Network (CT-ESN) and Echo State Networks (ESN). It opens into Echo State Networks (ESN) and Continuous-Time Echo State Network (CT-ESN)."},{"id":"taxonomy","type":"bullets","title":"Field Position","items":["Classification pending in the source taxonomy lookup."]},{"id":"connections","type":"bullets","title":"Connection Map","items":["Related: Continuous-Time Echo State Network (CT-ESN), Echo State Networks (ESN), State Space, State of the Art","Next: Echo State Networks (ESN), Continuous-Time Echo State Network (CT-ESN)"]},{"id":"study-prompts","type":"steps","title":"Study Prompts","steps":[{"label":"Find nearby concepts","body":"Locate the closest neighboring concepts before memorizing a phrasing."},{"label":"Define it","body":"Write the term in your own words before memorizing a textbook phrasing."},{"label":"Trace the graph","body":"Follow one prerequisite and one downstream concept from the learning graph."},{"label":"Record an example","body":"Capture an example, use case, or implementation note in your personal notebook."}]},{"id":"why-it-matters","type":"markdown","title":"Why It Matters","body":"Watch how it behaves relative to nearby concepts in the learning graph."},{"id":"comparison-notes","type":"bullets","title":"Comparison Notes","items":["Compare it with Continuous-Time Echo State Network (CT-ESN) and Echo State Networks (ESN) to separate overlap from difference.","After this term, continue into Echo State Networks (ESN) and Continuous-Time Echo State Network (CT-ESN)."]},{"id":"recall-drill","type":"steps","title":"Recall Drill","steps":[{"label":"Say it simply","body":"Rewrite Echo State Networks in one sentence before trying to preserve the source wording."},{"label":"Place it","body":"Watch how it behaves relative to nearby concepts in the learning graph."},{"label":"Link it","body":"Connect it to Continuous-Time Echo State Network (CT-ESN) and Echo State Networks (ESN) and one downstream idea from the graph."},{"label":"Review first","body":"If the term feels abstract, look at one nearby concept before returning to the main definition."}]},{"id":"at-a-glance","type":"table","title":"At a Glance","rows":[{"label":"Family","value":"Unclassified"},{"label":"Best first read","value":"Use the overview block"},{"label":"Best comparison","value":"Continuous-Time Echo State Network (CT-ESN) and Echo State Networks (ESN)"},{"label":"Next step","value":"Echo State Networks (ESN) and Continuous-Time Echo State Network (CT-ESN)"},{"label":"Remember","value":"Watch how it fits relative to nearby concepts in the learning graph."}]},{"id":"visual-summary","type":"callout","title":"Visual Summary","tone":"info","body":"Watch how it behaves relative to nearby concepts in the learning graph."},{"id":"curriculum-map","type":"curriculum-map","title":"Curriculum Map","sections":[{"section":"Introduction","status":"direct","runtimeBlocks":["overview","taxonomy"],"note":"The opening definition, context, and classification are always visible."},{"section":"Prerequisites","status":"direct","runtimeBlocks":["study-prompts","connections"],"note":"Prerequisite framing is handled by the study sequence and concept graph."},{"section":"Theoretical Concepts","status":"partial","runtimeBlocks":["overview","why-it-matters","recall-drill"],"note":"Core intuition is present, while deeper math-heavy expansion remains editorial backlog."},{"section":"How It Works","status":"direct","runtimeBlocks":["study-prompts","connections"],"note":"The step sequence and relation map carry the process explanation."},{"section":"Variants or Extensions","status":"direct","runtimeBlocks":["connections","comparison-notes"],"note":"Alternatives and neighboring labels are surfaced through graph and comparison blocks."},{"section":"Applications","status":"direct","runtimeBlocks":["overview","why-it-matters"],"note":"The summary and editorial note show relevance before deeper examples are added."},{"section":"Implementation","status":"direct","runtimeBlocks":["study-prompts","recall-drill"],"note":"Implementation thinking is supported by the guided sequence and recall practice."},{"section":"Evaluation and Metrics","status":"direct","runtimeBlocks":["comparison-notes","recall-drill"],"note":"Tradeoffs, comparison, and recall drills anchor evaluation thinking."},{"section":"Advantages and Disadvantages","status":"direct","runtimeBlocks":["comparison-notes","why-it-matters"],"note":"The current blocks already surface tradeoffs and framing."},{"section":"Ethics and Responsible AI","status":"direct","runtimeBlocks":["why-it-matters","comparison-notes"],"note":"Responsible-AI framing is visible in the editorial layer and comparison notes."},{"section":"Related Concepts","status":"direct","runtimeBlocks":["connections"],"note":"The concept graph is already a first-class runtime block."}]},{"id":"comparison","type":"comparison","title":"Compare and Contrast","panels":[{"label":"What it is","tone":"accent","body":"Echo State Networks is a glossary node in the AI/ML learning graph."},{"label":"What it is not","tone":"secondary","body":"It is not just Continuous-Time Echo State Network (CT-ESN) and Echo State Networks (ESN); the graph shows how it sits inside the nearby graph."},{"label":"Common confusion","tone":"gold","body":"Ask how it differs from nearby concepts and what changes when the term is applied. Compare it against Continuous-Time Echo State Network (CT-ESN) and Echo State Networks (ESN) so the boundary stays visible instead of collapsing into a synonym pile."},{"label":"Best next step","tone":"accent","body":"Review the overview block first, then move toward Echo State Networks (ESN) and Continuous-Time Echo State Network (CT-ESN)."}],"takeaway":"The comparison view keeps Echo State Networks honest by showing the nearest neighbors, the real boundary, and the next study move."},{"id":"concept-map","type":"diagram","title":"Concept Map","center":{"label":"Echo State Networks","caption":"the nearby graph"},"lanes":[{"label":"Before","tone":"accent","items":[]},{"label":"Compare","tone":"secondary","items":["Continuous-Time Echo State Network (CT-ESN)","Echo State Networks (ESN)","State Space"]},{"label":"After","tone":"gold","items":["Echo State Networks (ESN)","Continuous-Time Echo State Network (CT-ESN)"]}],"takeaway":"Read Echo State Networks as a node inside its learning graph: predecessor concepts give context, neighbors sharpen comparison, and next concepts show where the topic expands."},{"id":"quick-faq","type":"faq","title":"Quick FAQ","items":[{"question":"What is Echo State Networks in one sentence?","answer":"Echo State Networks is a glossary node in the AI/ML learning graph. Compare it with Continuous-Time Echo State Network (CT-ESN) and Echo State Networks (ESN). It opens into Echo State Networks (ESN) and Continuous-Time Echo State Network (CT-ESN)."},{"question":"What should I know before studying Echo State Networks?","answer":"Use the broader the surrounding graph context, the overview block, and the comparison view to orient yourself. Ask how it differs from nearby concepts and what changes when the term is applied."},{"question":"What should I compare Echo State Networks with?","answer":"Compare it with Continuous-Time Echo State Network (CT-ESN) and Echo State Networks (ESN) before moving on to Echo State Networks (ESN) and Continuous-Time Echo State Network (CT-ESN)."}]},{"id":"quick-quiz","type":"quiz","title":"Quick Check","question":"How should you place Echo State Networks in the learning graph?","options":["Treat it as an isolated fact","Compare it with Continuous-Time Echo State Network (CT-ESN)","Ignore the taxonomy","Jump only to Echo State Networks (ESN)"],"answerIndex":1,"explanation":"Echo State Networks is easiest to understand by comparing it with Continuous-Time Echo State Network (CT-ESN), since neighbors expose overlap, difference, and boundary conditions."}],"metadata":{"difficulty":"","maturity":"source-imported","studyFamily":"","editorialTier":"standard"},"artifact":{"shardId":"ec"},"source":{"glossaryWorkbook":{"file":"data_glossary.xlsx","sheetName":"main","inventoryRows":[3113,3893,5417],"inventoryCells":["A5417","D3893","E3893","F3113"],"inventoryColumns":["A","D","E","F"],"sourceCells":[{"rowNumber":3113,"columnIndex":6,"columnLetter":"F"},{"rowNumber":3893,"columnIndex":4,"columnLetter":"D"},{"rowNumber":3893,"columnIndex":5,"columnLetter":"E"},{"rowNumber":5417,"columnIndex":1,"columnLetter":"A"}],"taxonomyRow":null,"definitionRow":null,"definitionBody":null}}},{"id":"echo-state-networks-esn","slug":"echo-state-networks-esn","title":"Echo State Networks (ESN)","aliases":["Echo State Networks","ESN"],"summary":"Echo State Networks (ESN) is a glossary node in the AI/ML learning graph. Start after Echo State Networks. It opens into Continuous-Time Echo State Network (CT-ESN).","taxonomy":{"topic":"Echo State Networks (ESN)","category":"","subCategory":"","tags":[]},"autoClassified":false,"links":{"prerequisites":["Echo State Networks"],"related":["Continuous-Time Echo State Network (CT-ESN)","Echo State Networks","Steady-State Genetic Algorithms","Recurrent State Space Models"],"alternatives":[],"next":["Continuous-Time Echo State Network (CT-ESN)"]},"blocks":[{"id":"overview","type":"markdown","title":"Overview","body":"Echo State Networks (ESN) is a glossary node in the AI/ML learning graph. Start after Echo State Networks. It opens into Continuous-Time Echo State Network (CT-ESN)."},{"id":"taxonomy","type":"bullets","title":"Field Position","items":["Classification pending in the source taxonomy lookup."]},{"id":"connections","type":"bullets","title":"Connection Map","items":["Prerequisites: Echo State Networks","Related: Continuous-Time Echo State Network (CT-ESN), Echo State Networks, Steady-State Genetic Algorithms, Recurrent State Space Models","Next: Continuous-Time Echo State Network (CT-ESN)"]},{"id":"study-prompts","type":"steps","title":"Study Prompts","steps":[{"label":"Find nearby concepts","body":"Locate the closest neighboring concepts before memorizing a phrasing."},{"label":"Define it","body":"Write the term in your own words before memorizing a textbook phrasing."},{"label":"Trace the graph","body":"Follow one prerequisite and one downstream concept from the learning graph."},{"label":"Record an example","body":"Capture an example, use case, or implementation note in your personal notebook."}]},{"id":"why-it-matters","type":"markdown","title":"Why It Matters","body":"Watch how it behaves relative to nearby concepts in the learning graph."},{"id":"comparison-notes","type":"bullets","title":"Comparison Notes","items":["Before this term, get comfortable with Echo State Networks.","Compare it with Continuous-Time Echo State Network (CT-ESN) and Echo State Networks to separate overlap from difference.","After this term, continue into Continuous-Time Echo State Network (CT-ESN)."]},{"id":"recall-drill","type":"steps","title":"Recall Drill","steps":[{"label":"Say it simply","body":"Rewrite Echo State Networks (ESN) in one sentence before trying to preserve the source wording."},{"label":"Place it","body":"Watch how it behaves relative to nearby concepts in the learning graph."},{"label":"Link it","body":"Connect it to Continuous-Time Echo State Network (CT-ESN) and Echo State Networks and one downstream idea from the graph."},{"label":"Review first","body":"Check Echo State Networks so you can see what this term assumes."}]},{"id":"at-a-glance","type":"table","title":"At a Glance","rows":[{"label":"Family","value":"Unclassified"},{"label":"Best first read","value":"Echo State Networks"},{"label":"Best comparison","value":"Continuous-Time Echo State Network (CT-ESN) and Echo State Networks"},{"label":"Next step","value":"Continuous-Time Echo State Network (CT-ESN)"},{"label":"Remember","value":"Watch how it fits relative to nearby concepts in the learning graph."}]},{"id":"visual-summary","type":"callout","title":"Visual Summary","tone":"info","body":"Watch how it behaves relative to nearby concepts in the learning graph."},{"id":"curriculum-map","type":"curriculum-map","title":"Curriculum Map","sections":[{"section":"Introduction","status":"direct","runtimeBlocks":["overview","taxonomy"],"note":"The opening definition, context, and classification are always visible."},{"section":"Prerequisites","status":"direct","runtimeBlocks":["study-prompts","connections"],"note":"Prerequisite framing is handled by the study sequence and concept graph."},{"section":"Theoretical Concepts","status":"partial","runtimeBlocks":["overview","why-it-matters","recall-drill"],"note":"Core intuition is present, while deeper math-heavy expansion remains editorial backlog."},{"section":"How It Works","status":"direct","runtimeBlocks":["study-prompts","connections"],"note":"The step sequence and relation map carry the process explanation."},{"section":"Variants or Extensions","status":"direct","runtimeBlocks":["connections","comparison-notes"],"note":"Alternatives and neighboring labels are surfaced through graph and comparison blocks."},{"section":"Applications","status":"direct","runtimeBlocks":["overview","why-it-matters"],"note":"The summary and editorial note show relevance before deeper examples are added."},{"section":"Implementation","status":"direct","runtimeBlocks":["study-prompts","recall-drill"],"note":"Implementation thinking is supported by the guided sequence and recall practice."},{"section":"Evaluation and Metrics","status":"direct","runtimeBlocks":["comparison-notes","recall-drill"],"note":"Tradeoffs, comparison, and recall drills anchor evaluation thinking."},{"section":"Advantages and Disadvantages","status":"direct","runtimeBlocks":["comparison-notes","why-it-matters"],"note":"The current blocks already surface tradeoffs and framing."},{"section":"Ethics and Responsible AI","status":"direct","runtimeBlocks":["why-it-matters","comparison-notes"],"note":"Responsible-AI framing is visible in the editorial layer and comparison notes."},{"section":"Related Concepts","status":"direct","runtimeBlocks":["connections"],"note":"The concept graph is already a first-class runtime block."}]},{"id":"comparison","type":"comparison","title":"Compare and Contrast","panels":[{"label":"What it is","tone":"accent","body":"Echo State Networks (ESN) is a glossary node in the AI/ML learning graph."},{"label":"What it is not","tone":"secondary","body":"It is not just Continuous-Time Echo State Network (CT-ESN) and Echo State Networks; the graph shows how it sits inside the nearby graph."},{"label":"Common confusion","tone":"gold","body":"Ask how it differs from nearby concepts and what changes when the term is applied. Compare it against Continuous-Time Echo State Network (CT-ESN) and Echo State Networks so the boundary stays visible instead of collapsing into a synonym pile."},{"label":"Best next step","tone":"accent","body":"Review Echo State Networks first, then move toward Continuous-Time Echo State Network (CT-ESN)."}],"takeaway":"The comparison view keeps Echo State Networks (ESN) honest by showing the nearest neighbors, the real boundary, and the next study move."},{"id":"concept-map","type":"diagram","title":"Concept Map","center":{"label":"Echo State Networks (ESN)","caption":"the nearby graph"},"lanes":[{"label":"Before","tone":"accent","items":["Echo State Networks"]},{"label":"Compare","tone":"secondary","items":["Continuous-Time Echo State Network (CT-ESN)","Echo State Networks","Steady-State Genetic Algorithms"]},{"label":"After","tone":"gold","items":["Continuous-Time Echo State Network (CT-ESN)"]}],"takeaway":"Read Echo State Networks (ESN) as a node inside its learning graph: predecessor concepts give context, neighbors sharpen comparison, and next concepts show where the topic expands."},{"id":"quick-faq","type":"faq","title":"Quick FAQ","items":[{"question":"What is Echo State Networks (ESN) in one sentence?","answer":"Echo State Networks (ESN) is a glossary node in the AI/ML learning graph. Start after Echo State Networks. It opens into Continuous-Time Echo State Network (CT-ESN)."},{"question":"What should I know before studying Echo State Networks (ESN)?","answer":"Start with Echo State Networks."},{"question":"What should I compare Echo State Networks (ESN) with?","answer":"Compare it with Continuous-Time Echo State Network (CT-ESN) and Echo State Networks before moving on to Continuous-Time Echo State Network (CT-ESN)."}]},{"id":"quick-quiz","type":"quiz","title":"Quick Check","question":"What should you review first before studying Echo State Networks (ESN)?","options":["Review Echo State Networks","Jump to Continuous-Time Echo State Network (CT-ESN)","Memorize the title only","Skip straight to the next topic"],"answerIndex":0,"explanation":"Echo State Networks (ESN) sits after Echo State Networks, so that prerequisite gives you the assumptions and vocabulary you need before the deeper block stack makes sense."}],"metadata":{"difficulty":"","maturity":"source-imported","studyFamily":"","editorialTier":"standard"},"artifact":{"shardId":"ec"},"source":{"glossaryWorkbook":{"file":"data_glossary.xlsx","sheetName":"main","inventoryRows":[3114,3894,5418],"inventoryCells":["A5418","D3894","E3894","F3114"],"inventoryColumns":["A","D","E","F"],"sourceCells":[{"rowNumber":3114,"columnIndex":6,"columnLetter":"F"},{"rowNumber":3894,"columnIndex":4,"columnLetter":"D"},{"rowNumber":3894,"columnIndex":5,"columnLetter":"E"},{"rowNumber":5418,"columnIndex":1,"columnLetter":"A"}],"taxonomyRow":null,"definitionRow":null,"definitionBody":null}}},{"id":"eclat-algorithm","slug":"eclat-algorithm","title":"Eclat Algorithm","aliases":[],"summary":"Eclat Algorithm belongs to the Optimization Algorithms area of AI/ML. It sits inside Optimization Algorithms. Compare it with Yogi Optimizer and YellowFin Optimizer.","taxonomy":{"topic":"Eclat Algorithm","category":"Optimization Algorithms","subCategory":"","tags":["optimization-algorithms"]},"autoClassified":true,"links":{"prerequisites":[],"related":["Yogi Optimizer","YellowFin Optimizer","VDAM Optimizer","TORA Optimizer"],"alternatives":[],"next":[]},"blocks":[{"id":"overview","type":"markdown","title":"Overview","body":"Eclat Algorithm belongs to the Optimization Algorithms area of AI/ML. It sits inside Optimization Algorithms. Compare it with Yogi Optimizer and YellowFin Optimizer."},{"id":"taxonomy","type":"bullets","title":"Field Position","items":["Category: Optimization Algorithms"]},{"id":"connections","type":"bullets","title":"Connection Map","items":["Related: Yogi Optimizer, YellowFin Optimizer, VDAM Optimizer, TORA Optimizer"]},{"id":"study-prompts","type":"steps","title":"Study Prompts","steps":[{"label":"Situate it","body":"Place this term inside Optimization Algorithms before you memorize the wording."},{"label":"Define it","body":"Write the term in your own words before memorizing a textbook phrasing."},{"label":"Trace the graph","body":"Follow one prerequisite and one downstream concept from the learning graph."},{"label":"Record an example","body":"Capture an example, use case, or implementation note in your personal notebook."}]},{"id":"why-it-matters","type":"markdown","title":"Why It Matters","body":"Watch how it fits inside Optimization Algorithms and how nearby concepts narrow or extend the idea."},{"id":"comparison-notes","type":"bullets","title":"Comparison Notes","items":["Compare it with Yogi Optimizer and YellowFin Optimizer to separate overlap from difference."]},{"id":"recall-drill","type":"steps","title":"Recall Drill","steps":[{"label":"Say it simply","body":"Rewrite Eclat Algorithm in one sentence before trying to preserve the source wording."},{"label":"Place it","body":"Watch how it fits inside Optimization Algorithms and how nearby concepts narrow or extend the idea."},{"label":"Link it","body":"Connect it to Yogi Optimizer and YellowFin Optimizer and one downstream idea from the graph."},{"label":"Review first","body":"If the term feels abstract, look at one nearby concept before returning to the main definition."}]},{"id":"at-a-glance","type":"table","title":"At a Glance","rows":[{"label":"Family","value":"Optimization Algorithms"},{"label":"Best first read","value":"Use the overview block"},{"label":"Best comparison","value":"Yogi Optimizer and YellowFin Optimizer"},{"label":"Next step","value":"Use the recall drill"},{"label":"Remember","value":"Watch how it fits relative to nearby concepts in the learning graph."}]},{"id":"visual-summary","type":"callout","title":"Visual Summary","tone":"info","body":"Watch how it fits inside Optimization Algorithms and how nearby concepts narrow or extend the idea."},{"id":"curriculum-map","type":"curriculum-map","title":"Curriculum Map","sections":[{"section":"Introduction","status":"direct","runtimeBlocks":["overview","taxonomy"],"note":"The opening definition, context, and classification are always visible."},{"section":"Prerequisites","status":"direct","runtimeBlocks":["study-prompts","connections"],"note":"Prerequisite framing is handled by the study sequence and concept graph."},{"section":"Theoretical Concepts","status":"partial","runtimeBlocks":["overview","why-it-matters","recall-drill"],"note":"Core intuition is present, while deeper math-heavy expansion remains editorial backlog."},{"section":"How It Works","status":"direct","runtimeBlocks":["study-prompts","connections"],"note":"The step sequence and relation map carry the process explanation."},{"section":"Variants or Extensions","status":"direct","runtimeBlocks":["connections","comparison-notes"],"note":"Alternatives and neighboring labels are surfaced through graph and comparison blocks."},{"section":"Applications","status":"direct","runtimeBlocks":["overview","why-it-matters"],"note":"The summary and editorial note show relevance before deeper examples are added."},{"section":"Implementation","status":"direct","runtimeBlocks":["study-prompts","recall-drill"],"note":"Implementation thinking is supported by the guided sequence and recall practice."},{"section":"Evaluation and Metrics","status":"direct","runtimeBlocks":["comparison-notes","recall-drill"],"note":"Tradeoffs, comparison, and recall drills anchor evaluation thinking."},{"section":"Advantages and Disadvantages","status":"direct","runtimeBlocks":["comparison-notes","why-it-matters"],"note":"The current blocks already surface tradeoffs and framing."},{"section":"Ethics and Responsible AI","status":"direct","runtimeBlocks":["why-it-matters","comparison-notes"],"note":"Responsible-AI framing is visible in the editorial layer and comparison notes."},{"section":"Related Concepts","status":"direct","runtimeBlocks":["connections"],"note":"The concept graph is already a first-class runtime block."}]},{"id":"comparison","type":"comparison","title":"Compare and Contrast","panels":[{"label":"What it is","tone":"accent","body":"Eclat Algorithm belongs to the Optimization Algorithms area of AI/ML."},{"label":"What it is not","tone":"secondary","body":"It is not just Yogi Optimizer and YellowFin Optimizer; the graph shows how it sits inside Optimization Algorithms."},{"label":"Common confusion","tone":"gold","body":"Ask how it differs from nearby concepts and what changes when the term is applied. Compare it against Yogi Optimizer and YellowFin Optimizer so the boundary stays visible instead of collapsing into a synonym pile."},{"label":"Best next step","tone":"accent","body":"Review the overview block first, then move toward the next connected concept."}],"takeaway":"The comparison view keeps Eclat Algorithm honest by showing the nearest neighbors, the real boundary, and the next study move."},{"id":"concept-map","type":"diagram","title":"Concept Map","center":{"label":"Eclat Algorithm","caption":"Optimization Algorithms"},"lanes":[{"label":"Before","tone":"accent","items":[]},{"label":"Compare","tone":"secondary","items":["Yogi Optimizer","YellowFin Optimizer","VDAM Optimizer"]},{"label":"After","tone":"gold","items":[]}],"takeaway":"Read Eclat Algorithm as a node inside its learning graph: predecessor concepts give context, neighbors sharpen comparison, and next concepts show where the topic expands."},{"id":"quick-faq","type":"faq","title":"Quick FAQ","items":[{"question":"What is Eclat Algorithm in one sentence?","answer":"Eclat Algorithm belongs to the Optimization Algorithms area of AI/ML. It sits inside Optimization Algorithms. Compare it with Yogi Optimizer and YellowFin Optimizer."},{"question":"What should I know before studying Eclat Algorithm?","answer":"Use the broader Optimization Algorithms context, the overview block, and the comparison view to orient yourself. Ask how it differs from nearby concepts and what changes when the term is applied."},{"question":"What should I compare Eclat Algorithm with?","answer":"Compare it with Yogi Optimizer and YellowFin Optimizer before moving on to ."}]},{"id":"quick-quiz","type":"quiz","title":"Quick Check","question":"How should you place Eclat Algorithm in the learning graph?","options":["Treat it as an isolated fact","Compare it with Yogi Optimizer","Ignore the taxonomy","Jump only to the next term"],"answerIndex":1,"explanation":"Eclat Algorithm is easiest to understand by comparing it with Yogi Optimizer, since neighbors expose overlap, difference, and boundary conditions."}],"metadata":{"difficulty":"","maturity":"source-imported","studyFamily":"Optimization Algorithms","editorialTier":"standard"},"artifact":{"shardId":"ec"},"source":{"glossaryWorkbook":{"file":"data_glossary.xlsx","sheetName":"main","inventoryRows":[3115,3895,5419],"inventoryCells":["A5419","D3895","E3895","F3115"],"inventoryColumns":["A","D","E","F"],"sourceCells":[{"rowNumber":3115,"columnIndex":6,"columnLetter":"F"},{"rowNumber":3895,"columnIndex":4,"columnLetter":"D"},{"rowNumber":3895,"columnIndex":5,"columnLetter":"E"},{"rowNumber":5419,"columnIndex":1,"columnLetter":"A"}],"taxonomyRow":0,"definitionRow":null,"definitionBody":null}}},{"id":"ecog-ai","slug":"ecog-ai","title":"ECoG AI","aliases":[],"summary":"ECoG AI is a glossary node in the AI/ML learning graph. Start after AI in Architecture and AI and Architecture.","taxonomy":{"topic":"ECoG AI","category":"","subCategory":"","tags":[]},"autoClassified":false,"links":{"prerequisites":["AI in Architecture","AI and Architecture"],"related":["AI in Architecture","AI and Architecture","Weak AI","Trustworthy AI"],"alternatives":[],"next":[]},"blocks":[{"id":"overview","type":"markdown","title":"Overview","body":"ECoG AI is a glossary node in the AI/ML learning graph. Start after AI in Architecture and AI and Architecture."},{"id":"taxonomy","type":"bullets","title":"Field Position","items":["Classification pending in the source taxonomy lookup."]},{"id":"connections","type":"bullets","title":"Connection Map","items":["Prerequisites: AI in Architecture, AI and Architecture","Related: AI in Architecture, AI and Architecture, Weak AI, Trustworthy AI"]},{"id":"study-prompts","type":"steps","title":"Study Prompts","steps":[{"label":"Find nearby concepts","body":"Locate the closest neighboring concepts before memorizing a phrasing."},{"label":"Define it","body":"Write the term in your own words before memorizing a textbook phrasing."},{"label":"Trace the graph","body":"Follow one prerequisite and one downstream concept from the learning graph."},{"label":"Record an example","body":"Capture an example, use case, or implementation note in your personal notebook."}]},{"id":"why-it-matters","type":"markdown","title":"Why It Matters","body":"Watch how it behaves relative to nearby concepts in the learning graph."},{"id":"comparison-notes","type":"bullets","title":"Comparison Notes","items":["Before this term, get comfortable with AI in Architecture and AI and Architecture.","Compare it with AI in Architecture and AI and Architecture to separate overlap from difference."]},{"id":"recall-drill","type":"steps","title":"Recall Drill","steps":[{"label":"Say it simply","body":"Rewrite ECoG AI in one sentence before trying to preserve the source wording."},{"label":"Place it","body":"Watch how it behaves relative to nearby concepts in the learning graph."},{"label":"Link it","body":"Connect it to AI in Architecture and AI and Architecture and one downstream idea from the graph."},{"label":"Review first","body":"Check AI in Architecture and AI and Architecture so you can see what this term assumes."}]},{"id":"at-a-glance","type":"table","title":"At a Glance","rows":[{"label":"Family","value":"Unclassified"},{"label":"Best first read","value":"AI in Architecture and AI and Architecture"},{"label":"Best comparison","value":"AI in Architecture and AI and Architecture"},{"label":"Next step","value":"Use the recall drill"},{"label":"Remember","value":"Watch how it fits relative to nearby concepts in the learning graph."}]},{"id":"visual-summary","type":"callout","title":"Visual Summary","tone":"info","body":"Watch how it behaves relative to nearby concepts in the learning graph."},{"id":"curriculum-map","type":"curriculum-map","title":"Curriculum Map","sections":[{"section":"Introduction","status":"direct","runtimeBlocks":["overview","taxonomy"],"note":"The opening definition, context, and classification are always visible."},{"section":"Prerequisites","status":"direct","runtimeBlocks":["study-prompts","connections"],"note":"Prerequisite framing is handled by the study sequence and concept graph."},{"section":"Theoretical Concepts","status":"partial","runtimeBlocks":["overview","why-it-matters","recall-drill"],"note":"Core intuition is present, while deeper math-heavy expansion remains editorial backlog."},{"section":"How It Works","status":"direct","runtimeBlocks":["study-prompts","connections"],"note":"The step sequence and relation map carry the process explanation."},{"section":"Variants or Extensions","status":"direct","runtimeBlocks":["connections","comparison-notes"],"note":"Alternatives and neighboring labels are surfaced through graph and comparison blocks."},{"section":"Applications","status":"direct","runtimeBlocks":["overview","why-it-matters"],"note":"The summary and editorial note show relevance before deeper examples are added."},{"section":"Implementation","status":"direct","runtimeBlocks":["study-prompts","recall-drill"],"note":"Implementation thinking is supported by the guided sequence and recall practice."},{"section":"Evaluation and Metrics","status":"direct","runtimeBlocks":["comparison-notes","recall-drill"],"note":"Tradeoffs, comparison, and recall drills anchor evaluation thinking."},{"section":"Advantages and Disadvantages","status":"direct","runtimeBlocks":["comparison-notes","why-it-matters"],"note":"The current blocks already surface tradeoffs and framing."},{"section":"Ethics and Responsible AI","status":"direct","runtimeBlocks":["why-it-matters","comparison-notes"],"note":"Responsible-AI framing is visible in the editorial layer and comparison notes."},{"section":"Related Concepts","status":"direct","runtimeBlocks":["connections"],"note":"The concept graph is already a first-class runtime block."}]},{"id":"comparison","type":"comparison","title":"Compare and Contrast","panels":[{"label":"What it is","tone":"accent","body":"ECoG AI is a glossary node in the AI/ML learning graph."},{"label":"What it is not","tone":"secondary","body":"It is not just AI in Architecture and AI and Architecture; the graph shows how it sits inside the nearby graph."},{"label":"Common confusion","tone":"gold","body":"Ask how it differs from nearby concepts and what changes when the term is applied. Compare it against AI in Architecture and AI and Architecture so the boundary stays visible instead of collapsing into a synonym pile."},{"label":"Best next step","tone":"accent","body":"Review AI in Architecture and AI and Architecture first, then move toward the next connected concept."}],"takeaway":"The comparison view keeps ECoG AI honest by showing the nearest neighbors, the real boundary, and the next study move."},{"id":"concept-map","type":"diagram","title":"Concept Map","center":{"label":"ECoG AI","caption":"the nearby graph"},"lanes":[{"label":"Before","tone":"accent","items":["AI in Architecture","AI and Architecture"]},{"label":"Compare","tone":"secondary","items":["AI in Architecture","AI and Architecture","Weak AI"]},{"label":"After","tone":"gold","items":[]}],"takeaway":"Read ECoG AI as a node inside its learning graph: predecessor concepts give context, neighbors sharpen comparison, and next concepts show where the topic expands."},{"id":"quick-faq","type":"faq","title":"Quick FAQ","items":[{"question":"What is ECoG AI in one sentence?","answer":"ECoG AI is a glossary node in the AI/ML learning graph. Start after AI in Architecture and AI and Architecture."},{"question":"What should I know before studying ECoG AI?","answer":"Start with AI in Architecture and AI and Architecture."},{"question":"What should I compare ECoG AI with?","answer":"Compare it with AI in Architecture and AI and Architecture before moving on to ."}]},{"id":"quick-quiz","type":"quiz","title":"Quick Check","question":"What should you review first before studying ECoG AI?","options":["Review AI in Architecture","Jump to AI in Architecture","Memorize the title only","Skip straight to the next topic"],"answerIndex":0,"explanation":"ECoG AI sits after AI in Architecture, so that prerequisite gives you the assumptions and vocabulary you need before the deeper block stack makes sense."}],"metadata":{"difficulty":"","maturity":"source-imported","studyFamily":"","editorialTier":"standard"},"artifact":{"shardId":"ec"},"source":{"glossaryWorkbook":{"file":"data_glossary.xlsx","sheetName":"main","inventoryRows":[5420],"inventoryCells":["A5420"],"inventoryColumns":["A"],"sourceCells":[{"rowNumber":5420,"columnIndex":1,"columnLetter":"A"}],"taxonomyRow":null,"definitionRow":null,"definitionBody":null}}},{"id":"ecological-validity","slug":"ecological-validity","title":"Ecological Validity","aliases":[],"summary":"Ecological Validity is a glossary node in the AI/ML learning graph. Compare it with Scale Validity and Incremental Validity.","taxonomy":{"topic":"Ecological Validity","category":"","subCategory":"","tags":[]},"autoClassified":false,"links":{"prerequisites":[],"related":["Scale Validity","Incremental Validity","Face Validity","Statistical Validity"],"alternatives":[],"next":[]},"blocks":[{"id":"overview","type":"markdown","title":"Overview","body":"Ecological Validity is a glossary node in the AI/ML learning graph. Compare it with Scale Validity and Incremental Validity."},{"id":"taxonomy","type":"bullets","title":"Field Position","items":["Classification pending in the source taxonomy lookup."]},{"id":"connections","type":"bullets","title":"Connection Map","items":["Related: Scale Validity, Incremental Validity, Face Validity, Statistical Validity"]},{"id":"study-prompts","type":"steps","title":"Study Prompts","steps":[{"label":"Find nearby concepts","body":"Locate the closest neighboring concepts before memorizing a phrasing."},{"label":"Define it","body":"Write the term in your own words before memorizing a textbook phrasing."},{"label":"Trace the graph","body":"Follow one prerequisite and one downstream concept from the learning graph."},{"label":"Record an example","body":"Capture an example, use case, or implementation note in your personal notebook."}]},{"id":"why-it-matters","type":"markdown","title":"Why It Matters","body":"Watch how it behaves relative to nearby concepts in the learning graph."},{"id":"comparison-notes","type":"bullets","title":"Comparison Notes","items":["Compare it with Scale Validity and Incremental Validity to separate overlap from difference."]},{"id":"recall-drill","type":"steps","title":"Recall Drill","steps":[{"label":"Say it simply","body":"Rewrite Ecological Validity in one sentence before trying to preserve the source wording."},{"label":"Place it","body":"Watch how it behaves relative to nearby concepts in the learning graph."},{"label":"Link it","body":"Connect it to Scale Validity and Incremental Validity and one downstream idea from the graph."},{"label":"Review first","body":"If the term feels abstract, look at one nearby concept before returning to the main definition."}]},{"id":"at-a-glance","type":"table","title":"At a Glance","rows":[{"label":"Family","value":"Unclassified"},{"label":"Best first read","value":"Use the overview block"},{"label":"Best comparison","value":"Scale Validity and Incremental Validity"},{"label":"Next step","value":"Use the recall drill"},{"label":"Remember","value":"Watch how it fits relative to nearby concepts in the learning graph."}]},{"id":"visual-summary","type":"callout","title":"Visual Summary","tone":"info","body":"Watch how it behaves relative to nearby concepts in the learning graph."},{"id":"curriculum-map","type":"curriculum-map","title":"Curriculum Map","sections":[{"section":"Introduction","status":"direct","runtimeBlocks":["overview","taxonomy"],"note":"The opening definition, context, and classification are always visible."},{"section":"Prerequisites","status":"direct","runtimeBlocks":["study-prompts","connections"],"note":"Prerequisite framing is handled by the study sequence and concept graph."},{"section":"Theoretical Concepts","status":"partial","runtimeBlocks":["overview","why-it-matters","recall-drill"],"note":"Core intuition is present, while deeper math-heavy expansion remains editorial backlog."},{"section":"How It Works","status":"direct","runtimeBlocks":["study-prompts","connections"],"note":"The step sequence and relation map carry the process explanation."},{"section":"Variants or Extensions","status":"direct","runtimeBlocks":["connections","comparison-notes"],"note":"Alternatives and neighboring labels are surfaced through graph and comparison blocks."},{"section":"Applications","status":"direct","runtimeBlocks":["overview","why-it-matters"],"note":"The summary and editorial note show relevance before deeper examples are added."},{"section":"Implementation","status":"direct","runtimeBlocks":["study-prompts","recall-drill"],"note":"Implementation thinking is supported by the guided sequence and recall practice."},{"section":"Evaluation and Metrics","status":"direct","runtimeBlocks":["comparison-notes","recall-drill"],"note":"Tradeoffs, comparison, and recall drills anchor evaluation thinking."},{"section":"Advantages and Disadvantages","status":"direct","runtimeBlocks":["comparison-notes","why-it-matters"],"note":"The current blocks already surface tradeoffs and framing."},{"section":"Ethics and Responsible AI","status":"direct","runtimeBlocks":["why-it-matters","comparison-notes"],"note":"Responsible-AI framing is visible in the editorial layer and comparison notes."},{"section":"Related Concepts","status":"direct","runtimeBlocks":["connections"],"note":"The concept graph is already a first-class runtime block."}]},{"id":"comparison","type":"comparison","title":"Compare and Contrast","panels":[{"label":"What it is","tone":"accent","body":"Ecological Validity is a glossary node in the AI/ML learning graph."},{"label":"What it is not","tone":"secondary","body":"It is not just Scale Validity and Incremental Validity; the graph shows how it sits inside the nearby graph."},{"label":"Common confusion","tone":"gold","body":"Ask how it differs from nearby concepts and what changes when the term is applied. Compare it against Scale Validity and Incremental Validity so the boundary stays visible instead of collapsing into a synonym pile."},{"label":"Best next step","tone":"accent","body":"Review the overview block first, then move toward the next connected concept."}],"takeaway":"The comparison view keeps Ecological Validity honest by showing the nearest neighbors, the real boundary, and the next study move."},{"id":"concept-map","type":"diagram","title":"Concept Map","center":{"label":"Ecological Validity","caption":"the nearby graph"},"lanes":[{"label":"Before","tone":"accent","items":[]},{"label":"Compare","tone":"secondary","items":["Scale Validity","Incremental Validity","Face Validity"]},{"label":"After","tone":"gold","items":[]}],"takeaway":"Read Ecological Validity as a node inside its learning graph: predecessor concepts give context, neighbors sharpen comparison, and next concepts show where the topic expands."},{"id":"quick-faq","type":"faq","title":"Quick FAQ","items":[{"question":"What is Ecological Validity in one sentence?","answer":"Ecological Validity is a glossary node in the AI/ML learning graph. Compare it with Scale Validity and Incremental Validity."},{"question":"What should I know before studying Ecological Validity?","answer":"Use the broader the surrounding graph context, the overview block, and the comparison view to orient yourself. Ask how it differs from nearby concepts and what changes when the term is applied."},{"question":"What should I compare Ecological Validity with?","answer":"Compare it with Scale Validity and Incremental Validity before moving on to ."}]},{"id":"quick-quiz","type":"quiz","title":"Quick Check","question":"How should you place Ecological Validity in the learning graph?","options":["Treat it as an isolated fact","Compare it with Scale Validity","Ignore the taxonomy","Jump only to the next term"],"answerIndex":1,"explanation":"Ecological Validity is easiest to understand by comparing it with Scale Validity, since neighbors expose overlap, difference, and boundary conditions."}],"metadata":{"difficulty":"","maturity":"source-imported","studyFamily":"","editorialTier":"standard"},"artifact":{"shardId":"ec"},"source":{"glossaryWorkbook":{"file":"data_glossary.xlsx","sheetName":"main","inventoryRows":[3116,3896,5421],"inventoryCells":["A5421","D3896","E3896","F3116"],"inventoryColumns":["A","D","E","F"],"sourceCells":[{"rowNumber":3116,"columnIndex":6,"columnLetter":"F"},{"rowNumber":3896,"columnIndex":4,"columnLetter":"D"},{"rowNumber":3896,"columnIndex":5,"columnLetter":"E"},{"rowNumber":5421,"columnIndex":1,"columnLetter":"A"}],"taxonomyRow":null,"definitionRow":null,"definitionBody":null}}},{"id":"econml","slug":"econml","title":"EconML","aliases":[],"summary":"EconML is a glossary node in the AI/ML learning graph.","taxonomy":{"topic":"EconML","category":"","subCategory":"","tags":[]},"autoClassified":false,"links":{"prerequisites":[],"related":[],"alternatives":[],"next":[]},"blocks":[{"id":"overview","type":"markdown","title":"Overview","body":"EconML is a glossary node in the AI/ML learning graph."},{"id":"taxonomy","type":"bullets","title":"Field Position","items":["Classification pending in the source taxonomy lookup."]},{"id":"connections","type":"bullets","title":"Connection Map","items":["No promoted graph neighbors were available from the current import."]},{"id":"study-prompts","type":"steps","title":"Study Prompts","steps":[{"label":"Find nearby concepts","body":"Locate the closest neighboring concepts before memorizing a phrasing."},{"label":"Define it","body":"Write the term in your own words before memorizing a textbook phrasing."},{"label":"Trace the graph","body":"Follow one prerequisite and one downstream concept from the learning graph."},{"label":"Record an example","body":"Capture an example, use case, or implementation note in your personal notebook."}]},{"id":"why-it-matters","type":"markdown","title":"Why It Matters","body":"Watch how it behaves relative to nearby concepts in the learning graph."},{"id":"comparison-notes","type":"bullets","title":"Comparison Notes","items":["Use the taxonomy and the concept graph to place this term before you try to memorize a one-line definition."]},{"id":"recall-drill","type":"steps","title":"Recall Drill","steps":[{"label":"Say it simply","body":"Rewrite EconML in one sentence before trying to preserve the source wording."},{"label":"Place it","body":"Watch how it behaves relative to nearby concepts in the learning graph."},{"label":"Link it","body":"Connect it to a nearby neighbor and one downstream idea from the graph."},{"label":"Review first","body":"If the term feels abstract, look at one nearby concept before returning to the main definition."}]},{"id":"at-a-glance","type":"table","title":"At a Glance","rows":[{"label":"Family","value":"Unclassified"},{"label":"Best first read","value":"Use the overview block"},{"label":"Best comparison","value":"Use the connection map"},{"label":"Next step","value":"Use the recall drill"},{"label":"Remember","value":"Watch how it fits relative to nearby concepts in the learning graph."}]},{"id":"visual-summary","type":"callout","title":"Visual Summary","tone":"info","body":"Watch how it behaves relative to nearby concepts in the learning graph."},{"id":"curriculum-map","type":"curriculum-map","title":"Curriculum Map","sections":[{"section":"Introduction","status":"direct","runtimeBlocks":["overview","taxonomy"],"note":"The opening definition, context, and classification are always visible."},{"section":"Prerequisites","status":"direct","runtimeBlocks":["study-prompts","connections"],"note":"Prerequisite framing is handled by the study sequence and concept graph."},{"section":"Theoretical Concepts","status":"partial","runtimeBlocks":["overview","why-it-matters","recall-drill"],"note":"Core intuition is present, while deeper math-heavy expansion remains editorial backlog."},{"section":"How It Works","status":"direct","runtimeBlocks":["study-prompts","connections"],"note":"The step sequence and relation map carry the process explanation."},{"section":"Variants or Extensions","status":"direct","runtimeBlocks":["connections","comparison-notes"],"note":"Alternatives and neighboring labels are surfaced through graph and comparison blocks."},{"section":"Applications","status":"direct","runtimeBlocks":["overview","why-it-matters"],"note":"The summary and editorial note show relevance before deeper examples are added."},{"section":"Implementation","status":"direct","runtimeBlocks":["study-prompts","recall-drill"],"note":"Implementation thinking is supported by the guided sequence and recall practice."},{"section":"Evaluation and Metrics","status":"direct","runtimeBlocks":["comparison-notes","recall-drill"],"note":"Tradeoffs, comparison, and recall drills anchor evaluation thinking."},{"section":"Advantages and Disadvantages","status":"direct","runtimeBlocks":["comparison-notes","why-it-matters"],"note":"The current blocks already surface tradeoffs and framing."},{"section":"Ethics and Responsible AI","status":"direct","runtimeBlocks":["why-it-matters","comparison-notes"],"note":"Responsible-AI framing is visible in the editorial layer and comparison notes."},{"section":"Related Concepts","status":"direct","runtimeBlocks":["connections"],"note":"The concept graph is already a first-class runtime block."}]},{"id":"comparison","type":"comparison","title":"Compare and Contrast","panels":[{"label":"What it is","tone":"accent","body":"EconML is a glossary node in the AI/ML learning graph."},{"label":"What it is not","tone":"secondary","body":"It is not just an isolated vocabulary item; the graph shows how it sits inside the nearby graph."},{"label":"Common confusion","tone":"gold","body":"Ask how it differs from nearby concepts and what changes when the term is applied. Compare it against nearby concepts so the boundary stays visible instead of collapsing into a synonym pile."},{"label":"Best next step","tone":"accent","body":"Review the overview block first, then move toward the next connected concept."}],"takeaway":"The comparison view keeps EconML honest by showing the nearest neighbors, the real boundary, and the next study move."},{"id":"concept-map","type":"diagram","title":"Concept Map","center":{"label":"EconML","caption":"the nearby graph"},"lanes":[{"label":"Before","tone":"accent","items":[]},{"label":"Compare","tone":"secondary","items":[]},{"label":"After","tone":"gold","items":[]}],"takeaway":"Read EconML as a node inside its learning graph: predecessor concepts give context, neighbors sharpen comparison, and next concepts show where the topic expands."},{"id":"quick-faq","type":"faq","title":"Quick FAQ","items":[{"question":"What is EconML in one sentence?","answer":"EconML is a glossary node in the AI/ML learning graph."},{"question":"What should I know before studying EconML?","answer":"Use the broader the surrounding graph context, the overview block, and the comparison view to orient yourself. Ask how it differs from nearby concepts and what changes when the term is applied."},{"question":"What should I compare EconML with?","answer":"Compare it with the nearest concepts in the surrounding graph. Compare it with nearby concepts so the boundary stays visible."}]},{"id":"quick-quiz","type":"quiz","title":"Quick Check","question":"What is the safest way to place EconML?","options":["Use the broader learning graph to situate it before you memorize the wording.","Memorize the title only","Treat it as unrelated to the graph","Skip the overview and jump to exports"],"answerIndex":0,"explanation":"When specific links are sparse, the best anchor is the broader the nearby graph context plus the overview block, comparison view, and recall drill."}],"metadata":{"difficulty":"","maturity":"source-imported","studyFamily":"","editorialTier":"sparse"},"artifact":{"shardId":"ec"},"source":{"glossaryWorkbook":{"file":"data_glossary.xlsx","sheetName":"main","inventoryRows":[5422],"inventoryCells":["A5422"],"inventoryColumns":["A"],"sourceCells":[{"rowNumber":5422,"columnIndex":1,"columnLetter":"A"}],"taxonomyRow":null,"definitionRow":null,"definitionBody":null}}},{"id":"economic-agent","slug":"economic-agent","title":"Economic Agent","aliases":[],"summary":"Economic Agent belongs to the Reinforcement Learning area of AI/ML. It sits inside Reinforcement Learning. Start after Agent and Agent S.","taxonomy":{"topic":"Economic Agent","category":"Reinforcement Learning","subCategory":"","tags":["reinforcement-learning"]},"autoClassified":true,"links":{"prerequisites":["Agent","Agent S","Agent Architecture"],"related":["Agent S","Agent Architecture","Agent","\u03c00 Generalist Agent"],"alternatives":[],"next":[]},"blocks":[{"id":"overview","type":"markdown","title":"Overview","body":"Economic Agent belongs to the Reinforcement Learning area of AI/ML. It sits inside Reinforcement Learning. Start after Agent and Agent S."},{"id":"taxonomy","type":"bullets","title":"Field Position","items":["Category: Reinforcement Learning"]},{"id":"connections","type":"bullets","title":"Connection Map","items":["Prerequisites: Agent, Agent S, Agent Architecture","Related: Agent S, Agent Architecture, Agent, \u03c00 Generalist Agent"]},{"id":"study-prompts","type":"steps","title":"Study Prompts","steps":[{"label":"Situate it","body":"Place this term inside Reinforcement Learning before you memorize the wording."},{"label":"Define it","body":"Write the term in your own words before memorizing a textbook phrasing."},{"label":"Trace the graph","body":"Follow one prerequisite and one downstream concept from the learning graph."},{"label":"Record an example","body":"Capture an example, use case, or implementation note in your personal notebook."}]},{"id":"why-it-matters","type":"markdown","title":"Why It Matters","body":"Watch how the concept changes policy choice, reward structure, exploration, or control behavior."},{"id":"comparison-notes","type":"bullets","title":"Comparison Notes","items":["Before this term, get comfortable with Agent and Agent S.","Compare it with Agent S and Agent Architecture to separate overlap from difference."]},{"id":"recall-drill","type":"steps","title":"Recall Drill","steps":[{"label":"Say it simply","body":"Rewrite Economic Agent in one sentence before trying to preserve the source wording."},{"label":"Place it","body":"Watch how the concept changes policy choice, reward structure, exploration, or control behavior."},{"label":"Link it","body":"Connect it to Agent S and Agent Architecture and one downstream idea from the graph."},{"label":"Review first","body":"Check Agent and Agent S so you can see what this term assumes."}]},{"id":"at-a-glance","type":"table","title":"At a Glance","rows":[{"label":"Family","value":"Reinforcement Learning"},{"label":"Best first read","value":"Agent and Agent S"},{"label":"Best comparison","value":"Agent S and Agent Architecture"},{"label":"Next step","value":"Use the recall drill"},{"label":"Remember","value":"Watch how the concept changes policy choice, reward structure, exploration, or control behavior."}]},{"id":"visual-summary","type":"callout","title":"Visual Summary","tone":"info","body":"Watch how the concept changes policy choice, reward structure, exploration, or control behavior."},{"id":"curriculum-map","type":"curriculum-map","title":"Curriculum Map","sections":[{"section":"Introduction","status":"direct","runtimeBlocks":["overview","taxonomy"],"note":"The opening definition, context, and classification are always visible."},{"section":"Prerequisites","status":"direct","runtimeBlocks":["study-prompts","connections"],"note":"Prerequisite framing is handled by the study sequence and concept graph."},{"section":"Theoretical Concepts","status":"partial","runtimeBlocks":["overview","why-it-matters","recall-drill"],"note":"Core intuition is present, while deeper math-heavy expansion remains editorial backlog."},{"section":"How It Works","status":"direct","runtimeBlocks":["study-prompts","connections"],"note":"The step sequence and relation map carry the process explanation."},{"section":"Variants or Extensions","status":"direct","runtimeBlocks":["connections","comparison-notes"],"note":"Alternatives and neighboring labels are surfaced through graph and comparison blocks."},{"section":"Applications","status":"direct","runtimeBlocks":["overview","why-it-matters"],"note":"The summary and editorial note show relevance before deeper examples are added."},{"section":"Implementation","status":"direct","runtimeBlocks":["study-prompts","recall-drill"],"note":"Implementation thinking is supported by the guided sequence and recall practice."},{"section":"Evaluation and Metrics","status":"direct","runtimeBlocks":["comparison-notes","recall-drill"],"note":"Tradeoffs, comparison, and recall drills anchor evaluation thinking."},{"section":"Advantages and Disadvantages","status":"direct","runtimeBlocks":["comparison-notes","why-it-matters"],"note":"The current blocks already surface tradeoffs and framing."},{"section":"Ethics and Responsible AI","status":"direct","runtimeBlocks":["why-it-matters","comparison-notes"],"note":"Responsible-AI framing is visible in the editorial layer and comparison notes."},{"section":"Related Concepts","status":"direct","runtimeBlocks":["connections"],"note":"The concept graph is already a first-class runtime block."}]},{"id":"comparison","type":"comparison","title":"Compare and Contrast","panels":[{"label":"What it is","tone":"accent","body":"Economic Agent belongs to the Reinforcement Learning area of AI/ML."},{"label":"What it is not","tone":"secondary","body":"It is not just Agent S and Agent Architecture; the graph shows how it sits inside Reinforcement Learning."},{"label":"Common confusion","tone":"gold","body":"Ask whether the term changes policy, reward, exploration, or control dynamics. Compare it against Agent S and Agent Architecture so the boundary stays visible instead of collapsing into a synonym pile."},{"label":"Best next step","tone":"accent","body":"Review Agent and Agent S first, then move toward the next connected concept."}],"takeaway":"The comparison view keeps Economic Agent honest by showing the nearest neighbors, the real boundary, and the next study move."},{"id":"concept-map","type":"diagram","title":"Concept Map","center":{"label":"Economic Agent","caption":"Reinforcement Learning"},"lanes":[{"label":"Before","tone":"accent","items":["Agent","Agent S","Agent Architecture"]},{"label":"Compare","tone":"secondary","items":["Agent S","Agent Architecture","Agent"]},{"label":"After","tone":"gold","items":[]}],"takeaway":"Read Economic Agent as a node inside its learning graph: predecessor concepts give context, neighbors sharpen comparison, and next concepts show where the topic expands."},{"id":"quick-faq","type":"faq","title":"Quick FAQ","items":[{"question":"What is Economic Agent in one sentence?","answer":"Economic Agent belongs to the Reinforcement Learning area of AI/ML. It sits inside Reinforcement Learning. Start after Agent and Agent S."},{"question":"What should I know before studying Economic Agent?","answer":"Start with Agent and Agent S."},{"question":"What should I compare Economic Agent with?","answer":"Compare it with Agent S and Agent Architecture before moving on to ."}]},{"id":"quick-quiz","type":"quiz","title":"Quick Check","question":"What should you review first before studying Economic Agent?","options":["Review Agent","Jump to Agent S","Memorize the title only","Skip straight to the next topic"],"answerIndex":0,"explanation":"Economic Agent sits after Agent, so that prerequisite gives you the assumptions and vocabulary you need before the deeper block stack makes sense."}],"metadata":{"difficulty":"","maturity":"source-imported","studyFamily":"Reinforcement Learning","editorialTier":"standard"},"artifact":{"shardId":"ec"},"source":{"glossaryWorkbook":{"file":"data_glossary.xlsx","sheetName":"main","inventoryRows":[5423],"inventoryCells":["A5423"],"inventoryColumns":["A"],"sourceCells":[{"rowNumber":5423,"columnIndex":1,"columnLetter":"A"}],"taxonomyRow":0,"definitionRow":null,"definitionBody":null}}}]}
