{"id":"twin-rope-extrapolation","slug":"twin-rope-extrapolation","title":"Twin RoPE Extrapolation","aliases":[],"summary":"Twin RoPE Extrapolation belongs to the Neural Networks area of AI/ML, within Data Scaling. It sits inside Neural Networks / Data Scaling. Start after Twin Networks.","taxonomy":{"topic":"twin rope extrapolation","category":"Neural Networks","subCategory":"Data Scaling","tags":["neural-networks","data-scaling"]},"links":{"prerequisites":["Twin Networks"],"related":["Time-based Decay","Local receptive fields","Dual Batch Norm","Step-Decay / Time-based Decay"],"alternatives":[],"next":[]},"blocks":[{"id":"overview","type":"markdown","title":"Overview","body":"Twin RoPE Extrapolation belongs to the Neural Networks area of AI/ML, within Data Scaling. It sits inside Neural Networks / Data Scaling. Start after Twin Networks."},{"id":"taxonomy","type":"bullets","title":"Field Position","items":["Category: Neural Networks","Sub-category: Data Scaling"]},{"id":"connections","type":"bullets","title":"Connection Map","items":["Prerequisites: Twin Networks","Related: Time-based Decay, Local receptive fields, Dual Batch Norm, Step-Decay / Time-based Decay"]},{"id":"study-prompts","type":"steps","title":"Study Prompts","steps":[{"label":"Situate it","body":"Place this term inside Neural Networks / Data Scaling before you memorize the wording."},{"label":"Define it","body":"Write the term in your own words before memorizing a textbook phrasing."},{"label":"Trace the graph","body":"Follow one prerequisite and one downstream concept from the learning graph."},{"label":"Record an example","body":"Capture an example, use case, or implementation note in your personal notebook."}]},{"id":"why-it-matters","type":"markdown","title":"Why It Matters","body":"Watch how the concept affects layers, activations, gradients, optimization, or training dynamics."},{"id":"comparison-notes","type":"bullets","title":"Comparison Notes","items":["Before this term, get comfortable with Twin Networks.","Compare it with Time-based Decay and Local receptive fields to separate overlap from difference."]},{"id":"recall-drill","type":"steps","title":"Recall Drill","steps":[{"label":"Say it simply","body":"Rewrite Twin RoPE Extrapolation in one sentence before trying to preserve the source wording."},{"label":"Place it","body":"Watch how the concept affects layers, activations, gradients, optimization, or training dynamics."},{"label":"Link it","body":"Connect it to Time-based Decay and Local receptive fields and one downstream idea from the graph."},{"label":"Review first","body":"Check Twin Networks so you can see what this term assumes."}]},{"id":"at-a-glance","type":"table","title":"At a Glance","rows":[{"label":"Family","value":"Neural Networks / Data Scaling"},{"label":"Best first read","value":"Twin Networks"},{"label":"Best comparison","value":"Time-based Decay and Local receptive fields"},{"label":"Next step","value":"Use the recall drill"},{"label":"Remember","value":"Watch how the concept affects layers, activations, gradients, optimization, or training dynamics."}]},{"id":"visual-summary","type":"callout","title":"Visual Summary","tone":"info","body":"Watch how the concept affects layers, activations, gradients, optimization, or training dynamics."},{"id":"curriculum-map","type":"curriculum-map","title":"Curriculum Map","sections":[{"section":"Introduction","status":"direct","runtimeBlocks":["overview","taxonomy"],"note":"The opening definition, context, and classification are always visible."},{"section":"Prerequisites","status":"direct","runtimeBlocks":["study-prompts","connections"],"note":"Prerequisite framing is handled by the study sequence and concept graph."},{"section":"Theoretical Concepts","status":"partial","runtimeBlocks":["overview","why-it-matters","recall-drill"],"note":"Core intuition is present, while deeper math-heavy expansion remains editorial backlog."},{"section":"How It Works","status":"direct","runtimeBlocks":["study-prompts","connections"],"note":"The step sequence and relation map carry the process explanation."},{"section":"Variants or Extensions","status":"direct","runtimeBlocks":["connections","comparison-notes"],"note":"Alternatives and neighboring labels are surfaced through graph and comparison blocks."},{"section":"Applications","status":"direct","runtimeBlocks":["overview","why-it-matters"],"note":"The summary and editorial note show relevance before deeper examples are added."},{"section":"Implementation","status":"direct","runtimeBlocks":["study-prompts","recall-drill"],"note":"Implementation thinking is supported by the guided sequence and recall practice."},{"section":"Evaluation and Metrics","status":"direct","runtimeBlocks":["comparison-notes","recall-drill"],"note":"Tradeoffs, comparison, and recall drills anchor evaluation thinking."},{"section":"Advantages and Disadvantages","status":"direct","runtimeBlocks":["comparison-notes","why-it-matters"],"note":"The current blocks already surface tradeoffs and framing."},{"section":"Ethics and Responsible AI","status":"direct","runtimeBlocks":["why-it-matters","comparison-notes"],"note":"Responsible-AI framing is visible in the editorial layer and comparison notes."},{"section":"Related Concepts","status":"direct","runtimeBlocks":["connections"],"note":"The concept graph is already a first-class runtime block."}]},{"id":"structure-expansion","type":"structure-expansion","title":"Structure Expansion","sections":[{"section":"Historical Context","layer":"editorial-expansion","fieldCount":11,"firstColumnIndex":76,"lastColumnIndex":86,"sampleFields":["Historical Context - Origin and Evolution","Historical Context - Significant Milestones or Breakthroughs","Historical Context - Key Contributors or Researchers"]},{"section":"Glossary","layer":"editorial-expansion","fieldCount":8,"firstColumnIndex":204,"lastColumnIndex":211,"sampleFields":["Glossary - Definition of Key Terms","Glossary - Acronyms and Abbreviations","Glossary - Related Concepts or Jargon"]},{"section":"Case Studies","layer":"editorial-expansion","fieldCount":7,"firstColumnIndex":102,"lastColumnIndex":108,"sampleFields":["Case Studies - In-depth Analysis of Real-world Applications","Case Studies - Success Stories and Lessons Learned","Case Studies - Challenges and Solutions"]},{"section":"Further Reading","layer":"editorial-expansion","fieldCount":7,"firstColumnIndex":164,"lastColumnIndex":170,"sampleFields":["Further Reading - Recommended Books or Articles","Further Reading - Online Tutorials or Guides","Further Reading - Video Lectures or Podcasts"]},{"section":"Future Directions","layer":"editorial-expansion","fieldCount":7,"firstColumnIndex":197,"lastColumnIndex":203,"sampleFields":["Future Directions - Current Research Trends and Open Problems","Future Directions - Potential Future Developments or Improvements","Future Directions - Emerging Applications or Domains"]},{"section":"Hands-on Tutorials","layer":"editorial-expansion","fieldCount":7,"firstColumnIndex":116,"lastColumnIndex":122,"sampleFields":["Hands-on Tutorials - Step-by-Step Guides for Implementing Techniques","Hands-on Tutorials - Detailed Explanations of Code and Libraries","Hands-on Tutorials - Troubleshooting Common Issues - Common Errors or Misconfigurations"]},{"section":"Industry Insights","layer":"editorial-expansion","fieldCount":7,"firstColumnIndex":130,"lastColumnIndex":136,"sampleFields":["Industry Insights - Trends and Adoption in Different Sectors","Industry Insights - Challenges and Opportunities in Specific Domains","Industry Insights - Regulatory Landscape and Implications"]},{"section":"Real-world Datasets and Benchmarks","layer":"editorial-expansion","fieldCount":7,"firstColumnIndex":142,"lastColumnIndex":148,"sampleFields":["Real-world Datasets and Benchmarks - Popular Datasets for Training and Testing","Real-world Datasets and Benchmarks - Benchmark Results and Leaderboards","Real-world Datasets and Benchmarks - Data Preparation and Preprocessing Techniques"]}]},{"id":"comparison","type":"comparison","title":"Compare and Contrast","panels":[{"label":"What it is","tone":"accent","body":"Twin RoPE Extrapolation belongs to the Neural Networks area of AI/ML, within Data Scaling."},{"label":"What it is not","tone":"secondary","body":"It is not just Time-based Decay and Local receptive fields; the graph shows how it sits inside Neural Networks."},{"label":"Common confusion","tone":"gold","body":"Ask whether the term changes layers, activations, gradients, optimization, or training dynamics. Compare it against Time-based Decay and Local receptive fields so the boundary stays visible instead of collapsing into a synonym pile."},{"label":"Best next step","tone":"accent","body":"Review Twin Networks first, then move toward the next connected concept."}],"takeaway":"The comparison view keeps Twin RoPE Extrapolation honest by showing the nearest neighbors, the real boundary, and the next study move."},{"id":"concept-map","type":"diagram","title":"Concept Map","center":{"label":"Twin RoPE Extrapolation","caption":"Neural Networks / Data Scaling"},"lanes":[{"label":"Before","tone":"accent","items":["Twin Networks"]},{"label":"Compare","tone":"secondary","items":["Time-based Decay","Local receptive fields","Dual Batch Norm"]},{"label":"After","tone":"gold","items":[]}],"takeaway":"Read Twin RoPE Extrapolation as a node inside its learning graph: predecessor concepts give context, neighbors sharpen comparison, and next concepts show where the topic expands."},{"id":"quick-faq","type":"faq","title":"Quick FAQ","items":[{"question":"What is Twin RoPE Extrapolation in one sentence?","answer":"Twin RoPE Extrapolation belongs to the Neural Networks area of AI/ML, within Data Scaling. It sits inside Neural Networks / Data Scaling. Start after Twin Networks."},{"question":"What should I know before studying Twin RoPE Extrapolation?","answer":"Start with Twin Networks."},{"question":"What should I compare Twin RoPE Extrapolation with?","answer":"Compare it with Time-based Decay and Local receptive fields before moving on to ."}]},{"id":"quick-quiz","type":"quiz","title":"Quick Check","question":"What should you review first before studying Twin RoPE Extrapolation?","options":["Review Twin Networks","Jump to Time-based Decay","Memorize the title only","Skip straight to the next topic"],"answerIndex":0,"explanation":"Twin RoPE Extrapolation sits after Twin Networks, so that prerequisite gives you the assumptions and vocabulary you need before the deeper block stack makes sense."}],"metadata":{"difficulty":"","maturity":"source-imported","studyFamily":"Neural Networks","editorialTier":"standard","autoClassified":false,"taxonomySource":"registry"},"artifact":{"shardId":"tw"},"source":{"glossaryWorkbook":{"file":"data_glossary.xlsx","sheetName":"main","inventoryRows":[16183],"inventoryCells":["A16183"],"inventoryColumns":["A"],"sourceCells":[{"rowNumber":16183,"columnIndex":1,"columnLetter":"A"}],"taxonomyRow":-1,"definitionRow":null,"definitionBody":null}}}
