{"id":"unsupervised-representation-learning","slug":"unsupervised-representation-learning","title":"Unsupervised Representation Learning","aliases":[],"summary":"Learning representations from unlabeled data, often using techniques like autoencoders and contrastive learning. It sits inside Representation Learning / Feature Learning. Start after Unsupervised Learning and Q-Learning.","taxonomy":{"topic":"Unsupervised Representation Learning","category":"Representation Learning","subCategory":"Feature Learning","tags":["representation-learning","feature-learning"]},"autoClassified":false,"links":{"prerequisites":["Unsupervised Learning","Q-Learning","V-Learning"],"related":["Disentangled Representation Learning","Feature Learning","Domain-invariant Feature Learning","Sparse Coding"],"alternatives":[],"next":[]},"blocks":[{"id":"overview","type":"markdown","title":"Overview","body":"Learning representations from unlabeled data, often using techniques like autoencoders and contrastive learning. It sits inside Representation Learning / Feature Learning. Start after Unsupervised Learning and Q-Learning."},{"id":"taxonomy","type":"bullets","title":"Field Position","items":["Category: Representation Learning","Sub-category: Feature Learning"]},{"id":"connections","type":"bullets","title":"Connection Map","items":["Prerequisites: Unsupervised Learning, Q-Learning, V-Learning","Related: Disentangled Representation Learning, Feature Learning, Domain-invariant Feature Learning, Sparse Coding"]},{"id":"study-prompts","type":"steps","title":"Study Prompts","steps":[{"label":"Situate it","body":"Place this term inside Representation Learning / Feature Learning before you memorize the wording."},{"label":"Define it","body":"Write the term in your own words before memorizing a textbook phrasing."},{"label":"Trace the graph","body":"Follow one prerequisite and one downstream concept from the learning graph."},{"label":"Record an example","body":"Capture an example, use case, or implementation note in your personal notebook."}]},{"id":"why-it-matters","type":"markdown","title":"Why It Matters","body":"Watch how it fits inside Representation Learning / Feature Learning and how the neighboring terms change its meaning."},{"id":"comparison-notes","type":"bullets","title":"Comparison Notes","items":["Before this term, get comfortable with Unsupervised Learning and Q-Learning.","Compare it with Disentangled Representation Learning and Feature Learning to separate overlap from difference."]},{"id":"recall-drill","type":"steps","title":"Recall Drill","steps":[{"label":"Say it simply","body":"Rewrite Unsupervised Representation Learning in one sentence before trying to preserve the source wording."},{"label":"Place it","body":"Watch how it fits inside Representation Learning / Feature Learning and how the neighboring terms change its meaning."},{"label":"Link it","body":"Connect it to Disentangled Representation Learning and Feature Learning and one downstream idea from the graph."},{"label":"Review first","body":"Check Unsupervised Learning and Q-Learning so you can see what this term assumes."}]},{"id":"at-a-glance","type":"table","title":"At a Glance","rows":[{"label":"Family","value":"Representation Learning / Feature Learning"},{"label":"Best first read","value":"Unsupervised Learning and Q-Learning"},{"label":"Best comparison","value":"Disentangled Representation Learning and Feature Learning"},{"label":"Next step","value":"Use the recall drill"},{"label":"Remember","value":"Watch how it fits relative to nearby concepts in the learning graph."}]},{"id":"visual-summary","type":"callout","title":"Visual Summary","tone":"info","body":"Watch how it fits inside Representation Learning / Feature Learning and how the neighboring terms change its meaning."},{"id":"curriculum-map","type":"curriculum-map","title":"Curriculum Map","sections":[{"section":"Introduction","status":"direct","runtimeBlocks":["overview","taxonomy"],"note":"The opening definition, context, and classification are always visible."},{"section":"Prerequisites","status":"direct","runtimeBlocks":["study-prompts","connections"],"note":"Prerequisite framing is handled by the study sequence and concept graph."},{"section":"Theoretical Concepts","status":"partial","runtimeBlocks":["overview","why-it-matters","recall-drill"],"note":"Core intuition is present, while deeper math-heavy expansion remains editorial backlog."},{"section":"How It Works","status":"direct","runtimeBlocks":["study-prompts","connections"],"note":"The step sequence and relation map carry the process explanation."},{"section":"Variants or Extensions","status":"direct","runtimeBlocks":["connections","comparison-notes"],"note":"Alternatives and neighboring labels are surfaced through graph and comparison blocks."},{"section":"Applications","status":"direct","runtimeBlocks":["overview","why-it-matters"],"note":"The summary and editorial note show relevance before deeper examples are added."},{"section":"Implementation","status":"direct","runtimeBlocks":["study-prompts","recall-drill"],"note":"Implementation thinking is supported by the guided sequence and recall practice."},{"section":"Evaluation and Metrics","status":"direct","runtimeBlocks":["comparison-notes","recall-drill"],"note":"Tradeoffs, comparison, and recall drills anchor evaluation thinking."},{"section":"Advantages and Disadvantages","status":"direct","runtimeBlocks":["comparison-notes","why-it-matters"],"note":"The current blocks already surface tradeoffs and framing."},{"section":"Ethics and Responsible AI","status":"direct","runtimeBlocks":["why-it-matters","comparison-notes"],"note":"Responsible-AI framing is visible in the editorial layer and comparison notes."},{"section":"Related Concepts","status":"direct","runtimeBlocks":["connections"],"note":"The concept graph is already a first-class runtime block."}]},{"id":"structure-expansion","type":"structure-expansion","title":"Structure Expansion","sections":[{"section":"Metadata","layer":"backlog","fieldCount":47,"firstColumnIndex":238,"lastColumnIndex":284,"sampleFields":["Metadata - Term Validation and Basic Information - Recognition","Metadata - Term Validation and Basic Information - Abbreviations and Variations","Metadata - Term Validation and Basic Information - Standardization"]},{"section":"Interactive Elements","layer":"backlog","fieldCount":7,"firstColumnIndex":123,"lastColumnIndex":129,"sampleFields":["Interactive Elements - Quizzes or Assessments with Explanations","Interactive Elements - Interactive Visualizations or Simulations","Interactive Elements - Downloadable Code or Notebooks"]},{"section":"Interviews with Experts","layer":"backlog","fieldCount":7,"firstColumnIndex":109,"lastColumnIndex":115,"sampleFields":["Interviews with Experts - Q&A with Leading Researchers or Practitioners","Interviews with Experts - Insights into Current Trends and Future Directions","Interviews with Experts - Personal Experiences and Advice"]},{"section":"Did You Know?","layer":"backlog","fieldCount":6,"firstColumnIndex":154,"lastColumnIndex":159,"sampleFields":["Did You Know? - Interesting Facts or Trivia","Did You Know? - Common Misconceptions or Myths","Did You Know? - Latest Developments or Future Trends"]},{"section":"Recommended Websites and Courses","layer":"backlog","fieldCount":5,"firstColumnIndex":175,"lastColumnIndex":179,"sampleFields":["Recommended Websites and Courses - Online Learning Platforms","Recommended Websites and Courses - University Courses or Certifications","Recommended Websites and Courses - Industry-specific Resources"]},{"section":"Appendices","layer":"backlog","fieldCount":4,"firstColumnIndex":223,"lastColumnIndex":226,"sampleFields":["Appendices - Additional Resources and References","Appendices - Cheat Sheets or Quick Reference Guides","Appendices - Glossary of Terms and Definitions"]},{"section":"Collaboration and Community","layer":"backlog","fieldCount":4,"firstColumnIndex":180,"lastColumnIndex":183,"sampleFields":["Collaboration and Community - Online Forums and Discussion Platforms","Collaboration and Community - Open Source Projects and Contributions","Collaboration and Community - Conferences, Workshops, and Meetups"]},{"section":"Project Suggestions","layer":"backlog","fieldCount":4,"firstColumnIndex":171,"lastColumnIndex":174,"sampleFields":["Project Suggestions - Hands-on Exercises or Experiments","Project Suggestions - Real-world Problem-solving Tasks","Project Suggestions - Creative Applications or Extensions"]}]},{"id":"comparison","type":"comparison","title":"Compare and Contrast","panels":[{"label":"What it is","tone":"accent","body":"Learning representations from unlabeled data, often using techniques like autoencoders and contrastive learning."},{"label":"What it is not","tone":"secondary","body":"It is not just Disentangled Representation Learning and Feature Learning; the graph shows how it sits inside Representation Learning."},{"label":"Common confusion","tone":"gold","body":"Ask how it differs from nearby concepts and what changes when the term is applied. Compare it against Disentangled Representation Learning and Feature Learning so the boundary stays visible instead of collapsing into a synonym pile."},{"label":"Best next step","tone":"accent","body":"Review Unsupervised Learning and Q-Learning first, then move toward the next connected concept."}],"takeaway":"The comparison view keeps Unsupervised Representation Learning honest by showing the nearest neighbors, the real boundary, and the next study move."},{"id":"concept-map","type":"diagram","title":"Concept Map","center":{"label":"Unsupervised Representation Learning","caption":"Representation Learning / Feature Learning"},"lanes":[{"label":"Before","tone":"accent","items":["Unsupervised Learning","Q-Learning","V-Learning"]},{"label":"Compare","tone":"secondary","items":["Disentangled Representation Learning","Feature Learning","Domain-invariant Feature Learning"]},{"label":"After","tone":"gold","items":[]}],"takeaway":"Read Unsupervised Representation Learning as a node inside its learning graph: predecessor concepts give context, neighbors sharpen comparison, and next concepts show where the topic expands."},{"id":"quick-faq","type":"faq","title":"Quick FAQ","items":[{"question":"What is Unsupervised Representation Learning in one sentence?","answer":"Learning representations from unlabeled data, often using techniques like autoencoders and contrastive learning. It sits inside Representation Learning / Feature Learning. Start after Unsupervised Learning and Q-Learning."},{"question":"What should I know before studying Unsupervised Representation Learning?","answer":"Start with Unsupervised Learning and Q-Learning."},{"question":"What should I compare Unsupervised Representation Learning with?","answer":"Compare it with Disentangled Representation Learning and Feature Learning before moving on to ."}]},{"id":"quick-quiz","type":"quiz","title":"Quick Check","question":"What should you review first before studying Unsupervised Representation Learning?","options":["Review Unsupervised Learning","Jump to Disentangled Representation Learning","Memorize the title only","Skip straight to the next topic"],"answerIndex":0,"explanation":"Unsupervised Representation Learning sits after Unsupervised Learning, so that prerequisite gives you the assumptions and vocabulary you need before the deeper block stack makes sense."},{"id":"deep-dive","type":"deep-dive","title":"Featured Deep Dive","panels":[{"label":"Core idea","tone":"accent","body":"Learning representations from unlabeled data, often using techniques like autoencoders and contrastive learning."},{"label":"Place it","tone":"secondary","body":"Read it inside Representation Learning / Feature Learning before you try to memorize the wording."},{"label":"Compare it","tone":"gold","body":"Compare it with nearby concepts so the boundary stays visible. Use Disentangled Representation Learning and Feature Learning to see what this term is and what it is not."},{"label":"Move next","tone":"accent","body":"Start with Unsupervised Learning and Q-Learning, then move into the next connected concept."},{"label":"Memory hook","tone":"secondary","body":"Watch how it fits inside Representation Learning / Feature Learning and how the neighboring terms change its meaning."}],"takeaway":"Unsupervised Representation Learning deserves a deeper treatment because the surrounding graph gives enough signal to teach it as a concept, not just as a definition."},{"id":"source-definition","type":"markdown","title":"Source Definition Snippet","body":"Learning representations from unlabeled data, often using techniques like autoencoders and contrastive learning."}],"metadata":{"difficulty":"","maturity":"source-imported","studyFamily":"Representation Learning","editorialTier":"featured"},"artifact":{"shardId":"un"},"source":{"glossaryWorkbook":{"file":"data_glossary.xlsx","sheetName":"main","inventoryRows":[8555,8638,16346],"inventoryCells":["A16346","D8638","F8555"],"inventoryColumns":["A","D","F"],"sourceCells":[{"rowNumber":8555,"columnIndex":6,"columnLetter":"F"},{"rowNumber":8638,"columnIndex":4,"columnLetter":"D"},{"rowNumber":16346,"columnIndex":1,"columnLetter":"A"}],"taxonomyRow":625,"definitionRow":97,"definitionBody":"Learning representations from unlabeled data, often using techniques like autoencoders and contrastive learning."}}}
